{
  "main": {
    "id": "226f7a134dccaf72",
    "type": "split",
    "children": [
      {
        "id": "8c83a5b93d28c617",
        "type": "tabs",
        "children": [
          {
            "id": "fedb71e9db639eb3",
            "type": "leaf",
            "state": {
              "type": "empty",
              "state": {}
            }
          }
        ]
      }
    ],
    "direction": "vertical"
  },
  "left": {
    "id": "1154ddbc6ed8da06",
    "type": "split",
    "children": [
      {
        "id": "2e44f36c614b3b2a",
        "type": "tabs",
        "children": [
          {
            "id": "a9acd4f3165a9563",
            "type": "leaf",
            "state": {
              "type": "file-explorer",
              "state": {
                "sortOrder": "alphabetical"
              }
            }
          },
          {
            "id": "105fe7501e678c8b",
            "type": "leaf",
            "state": {
              "type": "search",
              "state": {
                "query": "",
                "matchingCase": false,
                "explainSearch": false,
                "collapseAll": false,
                "extraContext": false,
                "sortOrder": "alphabetical"
              }
            }
          },
          {
            "id": "b4ae1633e0448687",
            "type": "leaf",
            "state": {
              "type": "bookmarks",
              "state": {}
            }
          },
          {
            "id": "0051ef72ef0c3d8b",
            "type": "leaf",
            "state": {
              "type": "recent-files",
              "state": {}
            }
          }
        ]
      }
    ],
    "direction": "horizontal",
    "width": 300
  },
  "right": {
    "id": "749132619aec5ecc",
    "type": "split",
    "children": [
      {
        "id": "b80a504621ff0070",
        "type": "tabs",
        "children": [
          {
            "id": "6423ece86597aa05",
            "type": "leaf",
            "state": {
              "type": "backlink",
              "state": {
                "collapseAll": false,
                "extraContext": false,
                "sortOrder": "alphabetical",
                "showSearch": false,
                "searchQuery": "",
                "backlinkCollapsed": false,
                "unlinkedCollapsed": true
              }
            }
          },
          {
            "id": "860287ca1aea3f0f",
            "type": "leaf",
            "state": {
              "type": "outgoing-link",
              "state": {
                "linksCollapsed": false,
                "unlinkedCollapsed": true
              }
            }
          },
          {
            "id": "55fdc76411e3661c",
            "type": "leaf",
            "state": {
              "type": "tag",
              "state": {
                "sortOrder": "frequency",
                "useHierarchy": true
              }
            }
          },
          {
            "id": "53632e697a2893d6",
            "type": "leaf",
            "state": {
              "type": "outline",
              "state": {}
            }
          },
          {
            "id": "88910a5197994321",
            "type": "leaf",
            "state": {
              "type": "advanced-tables-toolbar",
              "state": {}
            }
          }
        ],
        "currentTab": 4
      }
    ],
    "direction": "horizontal",
    "width": 300,
    "collapsed": true
  },
  "left-ribbon": {
    "hiddenItems": {
      "switcher:Open quick switcher": false,
      "graph:Open graph view": false,
      "canvas:Create new canvas": false,
      "daily-notes:Open today's daily note": false,
      "templates:Insert template": false,
      "command-palette:Open command palette": false,
      "table-editor-obsidian:Advanced Tables Toolbar": false
    }
  },
  "active": "fedb71e9db639eb3",
  "lastOpenFiles": [
    "Obsidian Syntax.md",
    "Networking/Route Table.md",
    "Networking/AWS - VPC EC2 Subnet Connection with Internet.md",
    "Frontend/Cookies.md",
    "Mindstix Tasks/Give file permissions to LDAP groups.md",
    "Networking/Subnet.md",
    "Networking/SSH.md",
    "Networking/Socket.md",
    "Networking/NAT.md",
    "Mindstix Tasks",
    "Networking/VPC.md",
    "Networking/Virtual Machines vs Containers.md",
    "Bash/LS command.md",
    "Networking/Private IP Address.md",
    "Networking/Private and Public IP Address Space.md",
    "Networking/HTTP Headers.md",
    "Networking/Docker.md",
    "Networking/Subnett.md",
    "Images/Pasted image 20231012175606.png",
    "Bash",
    "Frontend",
    "Images",
    "Images/Pasted image 20231011155859.png",
    "Images/Pasted image 20231011130806.png",
    "Networking/Pasted image 20231011133530.png",
    "Private IP Address.md",
    "Networking/DHCP.md",
    "Networking",
    "2023-10-11.md"
  ]
}